<?xml version="1.0" encoding="UTF-8"?>
<typeSystemDescription xmlns="http://uima.apache.org/resourceSpecifier">
  <name>TypeSystem</name>
  <description>Type System Definition for the Breast Cancer Project</description>
  <version>1.0</version>
  <vendor>MAVERIC</vendor>
  <types>
    <typeDescription>
      <name>gov.va.maveric.uima.breastca.ReceptorStatus</name>
      <description/>
      <supertypeName>uima.tcas.Annotation</supertypeName>
      <features>
        <featureDescription>
          <name>receptorType</name>
          <description/>
          <rangeTypeName>uima.cas.String</rangeTypeName>
        </featureDescription>
        <featureDescription>
          <name>receptorStatus</name>
          <description/>
          <rangeTypeName>uima.cas.String</rangeTypeName>
        </featureDescription>
      </features>
    </typeDescription>
    <typeDescription>
      <name>gov.va.maveric.uima.breastca.TestType</name>
      <description/>
      <supertypeName>uima.tcas.Annotation</supertypeName>
      <features>
        <featureDescription>
          <name>testType</name>
          <description/>
          <rangeTypeName>uima.cas.String</rangeTypeName>
        </featureDescription>
      </features>
    </typeDescription>
    <typeDescription>
      <name>gov.va.maveric.uima.breastca.Stage</name>
      <description/>
      <supertypeName>uima.tcas.Annotation</supertypeName>
      <features>
        <featureDescription>
          <name>valueMain</name>
          <description/>
          <rangeTypeName>uima.cas.String</rangeTypeName>
        </featureDescription>
        <featureDescription>
          <name>valueModifier</name>
          <description/>
          <rangeTypeName>uima.cas.String</rangeTypeName>
        </featureDescription>
      </features>
    </typeDescription>
   <typeDescription>
      <name>gov.va.maveric.uima.breastca.Grade</name>
      <description/>
      <supertypeName>uima.tcas.Annotation</supertypeName>
      <features>
        <featureDescription>
          <name>grade</name>
          <description/>
          <rangeTypeName>uima.cas.String</rangeTypeName>
        </featureDescription>
      </features>
    </typeDescription>
   <typeDescription>
      <name>gov.va.maveric.uima.breastca.TNMDescriptor</name>
      <description/>
      <supertypeName>uima.tcas.Annotation</supertypeName>
      <features>
        <featureDescription>
          <name>t</name>
          <description/>
          <rangeTypeName>uima.cas.String</rangeTypeName>
        </featureDescription>
        <featureDescription>
          <name>tSub</name>
          <description/>
          <rangeTypeName>uima.cas.String</rangeTypeName>
        </featureDescription>
        <featureDescription>
          <name>n</name>
          <description/>
          <rangeTypeName>uima.cas.String</rangeTypeName>
        </featureDescription>
        <featureDescription>
          <name>nSub</name>
          <description/>
          <rangeTypeName>uima.cas.String</rangeTypeName>
        </featureDescription>
        <featureDescription>
          <name>m</name>
          <description/>
          <rangeTypeName>uima.cas.String</rangeTypeName>
        </featureDescription>
      </features>
    </typeDescription>
    <typeDescription>
      <name>gov.va.maveric.uima.breastca.Concept</name>
      <description/>
      <supertypeName>uima.tcas.Annotation</supertypeName>
      <features>
        <featureDescription>
          <name>features</name>
          <description/>
          <rangeTypeName>uima.cas.FSArray</rangeTypeName>
          <elementType>gov.va.maveric.uima.breastca.ConceptFeature</elementType>
        </featureDescription>
      </features>
    </typeDescription>
    <typeDescription>
      <name>gov.va.maveric.uima.breastca.ConceptFeature</name>
      <description/>
      <supertypeName>uima.tcas.Annotation</supertypeName>
      <features>
        <featureDescription>
          <name>name</name>
          <description/>
          <rangeTypeName>uima.cas.String</rangeTypeName>
        </featureDescription>
        <featureDescription>
          <name>value</name>
          <description/>
          <rangeTypeName>uima.cas.String</rangeTypeName>
        </featureDescription>
      </features>
    </typeDescription>
  </types>
</typeSystemDescription>
